{
	"items": [
		{
			"_id": "5c6687d65e9d882c8841f0fd",
			"_tpl": "55d7217a4bdc2d86028b456d"
		},
		{
			"_id": "5c6687d65e9d882c8841f121",
			"_tpl": "557ffd194bdc2d28148b457f",
			"parentId": "5c6687d65e9d882c8841f0fd",
			"slotId": "Pockets"
		},
		{
			"_id": "5c6687d65e9d882c8841f0fc",
			"_tpl": "566abbc34bdc2d92178b4576"
		},
		{
			"_id": "5c6687d65e9d882c8841f0ff",
			"_tpl": "5963866b86f7747bfa1c4462"
		},
		{
			"_id": "5c6687d65e9d882c8841f0fe",
			"_tpl": "5963866286f7747bf429b572"
		},
		{
			"_id": "TacticalVest205949",
			"_tpl": "5b44cad286f77402a54ae7e5",
			"parentId": "5c6687d65e9d882c8841f0fd",
			"slotId": "TacticalVest",
			"upd": {
				"SpawnedInSession": true
			}
		},
		{
			"_id": "I041558528535207261HIDZi",
			"_tpl": "59984ab886f7743e98271174",
			"parentId": "5c6687d65e9d882c8841f0fd",
			"slotId": "FirstPrimaryWeapon"
		},
		{
			"_id": "I041558527190789708r01Bs",
			"_tpl": "5beec8ea0db834001a6f9dbf",
			"parentId": "I041558528535207261HIDZi",
			"slotId": "mod_pistol_grip",
			"upd": {
				"SpawnedInSession": true
			}
		},
		{
			"_id": "I041558522386643571XJ3Ki",
			"_tpl": "5cf50fc5d7f00c056c53f83c",
			"parentId": "I041558528535207261HIDZi",
			"slotId": "mod_stock",
			"upd": {
				"SpawnedInSession": true
			}
		},
		{
			"_id": "I0415585219637695807QzVz",
			"_tpl": "5648ac824bdc2ded0b8b457d",
			"parentId": "I041558528535207261HIDZi",
			"slotId": "mod_charge",
			"upd": {
				"SpawnedInSession": true
			}
		},
		{
			"_id": "MagazineWeaponScav5346",
			"_tpl": "5998529a86f774647f44f421",
			"parentId": "I041558528535207261HIDZi",
			"slotId": "mod_magazine",
			"upd": {
				"SpawnedInSession": true
			}
		},
		{
			"_id": "AmmoMag18926",
			"_tpl": "58864a4f2459770fcc257101",
			"parentId": "MagazineWeaponScav5346",
			"slotId": "cartridges",
			"upd": {
				"SpawnedInSession": true,
				"StackObjectsCount": 10
			}
		},
		{
			"_id": "I041558529020583088HBJzv",
			"_tpl": "5c6165902e22160010261b28",
			"parentId": "I041558528535207261HIDZi",
			"slotId": "mod_muzzle",
			"upd": {
				"SpawnedInSession": true
			}
		},
		{
			"_id": "I041558522972114128sqzqK",
			"_tpl": "59985a6c86f77414ec448d17",
			"parentId": "I041558528535207261HIDZi",
			"slotId": "mod_reciever",
			"upd": {
				"SpawnedInSession": true
			}
		},
		{
			"_id": "I041558526288711931FM4R9",
			"_tpl": "59ccd11386f77428f24a488f",
			"parentId": "I041558528535207261HIDZi",
			"slotId": "mod_gas_block",
			"upd": {
				"SpawnedInSession": true
			}
		},
		{
			"_id": "I041558529369371673L1qfQ",
			"_tpl": "5a9eb32da2750c00171b3f9c",
			"parentId": "I041558522386643571XJ3Ki",
			"slotId": "mod_stock",
			"upd": {
				"SpawnedInSession": true
			}
		},
		{
			"_id": "I041558526116146249DZ5QN",
			"_tpl": "584924ec24597768f12ae244",
			"parentId": "I041558522972114128sqzqK",
			"slotId": "mod_scope",
			"upd": {
				"SpawnedInSession": true
			}
		},
		{
			"_id": "I041558529494527170caSZq",
			"_tpl": "5d4aaa73a4b9365392071175",
			"parentId": "I041558526288711931FM4R9",
			"slotId": "mod_handguard",
			"upd": {
				"SpawnedInSession": true
			}
		},
		{
			"_id": "I041558524272617478luDyI",
			"_tpl": "5b7be4895acfc400170e2dd5",
			"parentId": "I041558529494527170caSZq",
			"slotId": "mod_foregrip",
			"upd": {
				"SpawnedInSession": true
			}
		},
		{
			"_id": "I041558525772498920N9zjw",
			"_tpl": "5b7be47f5acfc400170e2dd2",
			"parentId": "I041558529494527170caSZq",
			"slotId": "mod_mount_000",
			"upd": {
				"SpawnedInSession": true
			}
		},
		{
			"_id": "I041558527494844543XnwBS",
			"_tpl": "58c157be86f77403c74b2bb6",
			"parentId": "I041558524272617478luDyI",
			"slotId": "mod_foregrip",
			"upd": {
				"SpawnedInSession": true
			}
		},
		{
			"_id": "I041558524492736215abixG",
			"_tpl": "5cc9c20cd7f00c001336c65d",
			"parentId": "I041558525772498920N9zjw",
			"slotId": "mod_tactical",
			"upd": {
				"SpawnedInSession": true
			}
		},
		{
			"_id": "mag0Vest468752",
			"_tpl": "599860ac86f77436b225ed1a",
			"parentId": "TacticalVest205949",
			"slotId": "1",
			"location": {
				"x": 0,
				"y": 0,
				"r": "Horizontal"
			},
			"upd": {
				"SpawnedInSession": true
			}
		},
		{
			"_id": "AmmoMag0Vest269481",
			"_tpl": "5a3c16fe86f77452b62de32a",
			"parentId": "mag0Vest468752",
			"slotId": "cartridges",
			"upd": {
				"SpawnedInSession": true,
				"StackObjectsCount": 30
			}
		},
		{
			"_id": "mag1Vest714612",
			"_tpl": "599860ac86f77436b225ed1a",
			"parentId": "TacticalVest205949",
			"slotId": "3",
			"location": {
				"x": 0,
				"y": 0,
				"r": "Horizontal"
			},
			"upd": {
				"SpawnedInSession": true
			}
		},
		{
			"_id": "AmmoMag1Vest487372",
			"_tpl": "58864a4f2459770fcc257101",
			"parentId": "mag1Vest714612",
			"slotId": "cartridges",
			"upd": {
				"SpawnedInSession": true,
				"StackObjectsCount": 30
			}
		},
		{
			"_id": "StackAmmo34568056080",
			"_tpl": "58864a4f2459770fcc257101",
			"parentId": "TacticalVest205949",
			"slotId": "6",
			"upd": {
				"SpawnedInSession": true,
				"StackObjectsCount": 9
			}
		},
		{
			"_id": "StackAmmo223119720",
			"_tpl": "5c0d56a986f774449d5de529",
			"parentId": "TacticalVest205949",
			"slotId": "11",
			"upd": {
				"SpawnedInSession": true,
				"StackObjectsCount": 6
			}
		},
		{
			"_id": "Scabbard112668",
			"_tpl": "57e26ea924597715ca604a09",
			"parentId": "5c6687d65e9d882c8841f0fd",
			"slotId": "Scabbard",
			"upd": {
				"SpawnedInSession": true
			}
		},
		{
			"_id": "Eyewear720340",
			"_tpl": "5d5fca1ea4b93635fd598c07",
			"parentId": "5c6687d65e9d882c8841f0fd",
			"slotId": "Eyewear",
			"upd": {
				"SpawnedInSession": true
			}
		},
		{
			"_id": "Backpack738608",
			"_tpl": "544a5cde4bdc2d39388b456b",
			"parentId": "5c6687d65e9d882c8841f0fd",
			"slotId": "Backpack",
			"upd": {
				"SpawnedInSession": true
			}
		},
		{
			"_id": "BP_Backpack738608_690518",
			"_tpl": "5b3f7c005acfc4704b4a1de8",
			"parentId": "Backpack738608",
			"slotId": "main",
			"location": {
				"x": 0,
				"y": 0,
				"r": "Horizontal"
			},
			"upd": {
				"SpawnedInSession": true
			}
		},
		{
			"_id": "BP_Backpack738608_378287",
			"_tpl": "59fc48e086f77463b1118392",
			"parentId": "Backpack738608",
			"slotId": "main",
			"location": {
				"x": 0,
				"y": 1,
				"r": "Horizontal"
			},
			"upd": {
				"SpawnedInSession": true
			}
		},
		{
			"_id": "ArmorVest836611",
			"_tpl": "5c0e541586f7747fa54205c9",
			"parentId": "5c6687d65e9d882c8841f0fd",
			"slotId": "ArmorVest",
			"upd": {
				"Repairable": {
					"MaxDurability": 60,
					"Durability": 41
				}
			}
		},
		{
			"_id": "Pocket_679311",
			"_tpl": "5d1b39a386f774252339976f",
			"parentId": "5c6687d65e9d882c8841f121",
			"slotId": "pocket1",
			"location": {
				"x": 0,
				"y": 0,
				"r": "Horizontal"
			},
			"upd": {
				"SpawnedInSession": true
			}
		},
		{
			"_id": "Pocket_570794",
			"_tpl": "590a3d9c86f774385926e510",
			"parentId": "5c6687d65e9d882c8841f121",
			"slotId": "pocket2",
			"location": {
				"x": 0,
				"y": 0,
				"r": "Horizontal"
			},
			"upd": {
				"SpawnedInSession": true
			}
		},
		{
			"_id": "Pocket_197698",
			"_tpl": "573476d324597737da2adc13",
			"parentId": "5c6687d65e9d882c8841f121",
			"slotId": "pocket3",
			"location": {
				"x": 0,
				"y": 0,
				"r": "Horizontal"
			},
			"upd": {
				"SpawnedInSession": true
			}
		}
	],
	"equipment": "5c6687d65e9d882c8841f0fd",
	"stash": "5c6687d65e9d882c8841f0fc",
	"questRaidItems": "5c6687d65e9d882c8841f0fe",
	"questStashItems": "5c6687d65e9d882c8841f0ff",
	"fastPanel": {}
}