{
	"items": [
		{
			"_id": "5c6687d65e9d882c8841f0fd",
			"_tpl": "55d7217a4bdc2d86028b456d"
		},
		{
			"_id": "5c6687d65e9d882c8841f121",
			"_tpl": "557ffd194bdc2d28148b457f",
			"parentId": "5c6687d65e9d882c8841f0fd",
			"slotId": "Pockets"
		},
		{
			"_id": "5c6687d65e9d882c8841f0fc",
			"_tpl": "566abbc34bdc2d92178b4576"
		},
		{
			"_id": "5c6687d65e9d882c8841f0ff",
			"_tpl": "5963866b86f7747bfa1c4462"
		},
		{
			"_id": "5c6687d65e9d882c8841f0fe",
			"_tpl": "5963866286f7747bf429b572"
		},
		{
			"_id": "TacticalVest753896",
			"_tpl": "592c2d1a86f7746dbe2af32a",
			"parentId": "5c6687d65e9d882c8841f0fd",
			"slotId": "TacticalVest",
			"upd": {
				"SpawnedInSession": true
			}
		},
		{
			"_id": "I041511507850704380WVt3o",
			"_tpl": "5b0bbe4e5acfc40dc528a72d",
			"parentId": "5c6687d65e9d882c8841f0fd",
			"slotId": "FirstPrimaryWeapon"
		},
		{
			"_id": "I041511504750026807c8blY",
			"_tpl": "5b099b965acfc400186331e6",
			"parentId": "I041511507850704380WVt3o",
			"slotId": "mod_pistol_grip",
			"upd": {
				"SpawnedInSession": true
			}
		},
		{
			"_id": "MagazineWeaponScav3603",
			"_tpl": "5b099ac65acfc400186331e1",
			"parentId": "I041511507850704380WVt3o",
			"slotId": "mod_magazine",
			"upd": {
				"SpawnedInSession": true
			}
		},
		{
			"_id": "AmmoMag1401",
			"_tpl": "5e023e6e34d52a55c3304f71",
			"parentId": "MagazineWeaponScav3603",
			"slotId": "cartridges",
			"upd": {
				"SpawnedInSession": true,
				"StackObjectsCount": 20
			}
		},
		{
			"_id": "I041511508439946512ztvS2",
			"_tpl": "5b099a9d5acfc47a8607efe7",
			"parentId": "I041511507850704380WVt3o",
			"slotId": "mod_handguard",
			"upd": {
				"SpawnedInSession": true
			}
		},
		{
			"_id": "I041511506059294972CBcP6",
			"_tpl": "5b099a765acfc47a8607efe3",
			"parentId": "I041511507850704380WVt3o",
			"slotId": "mod_barrel",
			"upd": {
				"SpawnedInSession": true
			}
		},
		{
			"_id": "I041511502198711510PbG0L",
			"_tpl": "5b099bb25acfc400186331e8",
			"parentId": "I041511507850704380WVt3o",
			"slotId": "mod_reciever",
			"upd": {
				"SpawnedInSession": true
			}
		},
		{
			"_id": "I041511501996127473mZIR9",
			"_tpl": "5b7d63de5acfc400170e2f8d",
			"parentId": "I041511507850704380WVt3o",
			"slotId": "mod_stock",
			"upd": {
				"SpawnedInSession": true
			}
		},
		{
			"_id": "I041511503437153026MwyFf",
			"_tpl": "588226d124597767ad33f787",
			"parentId": "I041511508439946512ztvS2",
			"slotId": "mod_foregrip",
			"upd": {
				"SpawnedInSession": true
			}
		},
		{
			"_id": "I041511509163740126LcqYn",
			"_tpl": "5649a2464bdc2d91118b45a8",
			"parentId": "I041511508439946512ztvS2",
			"slotId": "mod_mount",
			"upd": {
				"SpawnedInSession": true
			}
		},
		{
			"_id": "I041511504560382614qQHVy",
			"_tpl": "577d128124597739d65d0e56",
			"parentId": "I041511509163740126LcqYn",
			"slotId": "mod_scope",
			"upd": {
				"SpawnedInSession": true
			}
		},
		{
			"_id": "I041511507121464640om0Qe",
			"_tpl": "577d141e24597739c5255e01",
			"parentId": "I041511504560382614qQHVy",
			"slotId": "mod_scope",
			"upd": {
				"SpawnedInSession": true
			}
		},
		{
			"_id": "I041511508615817982kx7EE",
			"_tpl": "59bffc1f86f77435b128b872",
			"parentId": "I041511506059294972CBcP6",
			"slotId": "mod_muzzle",
			"upd": {
				"SpawnedInSession": true
			}
		},
		{
			"_id": "I041511502294094425xSkm9",
			"_tpl": "59bffbb386f77435b379b9c2",
			"parentId": "I041511508615817982kx7EE",
			"slotId": "mod_muzzle",
			"upd": {
				"SpawnedInSession": true
			}
		},
		{
			"_id": "I04151150209604326586Q1I",
			"_tpl": "57adff4f24597737f373b6e6",
			"parentId": "I041511502198711510PbG0L",
			"slotId": "mod_scope",
			"upd": {
				"SpawnedInSession": true
			}
		},
		{
			"_id": "mag0Vest369941",
			"_tpl": "5b7c2d1d5acfc43d1028532a",
			"parentId": "TacticalVest753896",
			"slotId": "6",
			"location": {
				"x": 0,
				"y": 0,
				"r": "Horizontal"
			},
			"upd": {
				"SpawnedInSession": true
			}
		},
		{
			"_id": "AmmoMag0Vest653326",
			"_tpl": "5e023e6e34d52a55c3304f71",
			"parentId": "mag0Vest369941",
			"slotId": "cartridges",
			"upd": {
				"SpawnedInSession": true,
				"StackObjectsCount": 20
			}
		},
		{
			"_id": "mag0Vest420436",
			"_tpl": "5b7c2d1d5acfc43d1028532a",
			"parentId": "TacticalVest753896",
			"slotId": "6",
			"location": {
				"x": 1,
				"y": 0,
				"r": "Horizontal"
			},
			"upd": {
				"SpawnedInSession": true
			}
		},
		{
			"_id": "AmmoMag0Vest999056",
			"_tpl": "5e023e88277cce2b522ff2b1",
			"parentId": "mag0Vest420436",
			"slotId": "cartridges",
			"upd": {
				"SpawnedInSession": true,
				"StackObjectsCount": 20
			}
		},
		{
			"_id": "Scabbard887974",
			"_tpl": "57e26ea924597715ca604a09",
			"parentId": "5c6687d65e9d882c8841f0fd",
			"slotId": "Scabbard",
			"upd": {
				"SpawnedInSession": true
			}
		},
		{
			"_id": "FaceCover298938",
			"_tpl": "5bd0716d86f774171822ef4b",
			"parentId": "5c6687d65e9d882c8841f0fd",
			"slotId": "FaceCover",
			"upd": {
				"SpawnedInSession": true
			}
		},
		{
			"_id": "Pocket_149676",
			"_tpl": "5938603e86f77435642354f4",
			"parentId": "5c6687d65e9d882c8841f121",
			"slotId": "pocket1",
			"location": {
				"x": 0,
				"y": 0,
				"r": "Horizontal"
			},
			"upd": {
				"SpawnedInSession": true
			}
		}
	],
	"equipment": "5c6687d65e9d882c8841f0fd",
	"stash": "5c6687d65e9d882c8841f0fc",
	"questRaidItems": "5c6687d65e9d882c8841f0fe",
	"questStashItems": "5c6687d65e9d882c8841f0ff",
	"fastPanel": {}
}