{
	"items": [
		{
			"_id": "5c6687d65e9d882c8841f0fd",
			"_tpl": "55d7217a4bdc2d86028b456d"
		},
		{
			"_id": "5c6687d65e9d882c8841f121",
			"_tpl": "557ffd194bdc2d28148b457f",
			"parentId": "5c6687d65e9d882c8841f0fd",
			"slotId": "Pockets"
		},
		{
			"_id": "5c6687d65e9d882c8841f0fc",
			"_tpl": "566abbc34bdc2d92178b4576"
		},
		{
			"_id": "5c6687d65e9d882c8841f0ff",
			"_tpl": "5963866b86f7747bfa1c4462"
		},
		{
			"_id": "5c6687d65e9d882c8841f0fe",
			"_tpl": "5963866286f7747bf429b572"
		},
		{
			"_id": "TacticalVest399026",
			"_tpl": "5d5d85c586f774279a21cbdb",
			"parentId": "5c6687d65e9d882c8841f0fd",
			"slotId": "TacticalVest",
			"upd": {
				"SpawnedInSession": true
			}
		},
		{
			"_id": "I04171229390613807dGFkuL",
			"_tpl": "5dcbd56fdbd3d91b3e5468d5",
			"parentId": "5c6687d65e9d882c8841f0fd",
			"slotId": "FirstPrimaryWeapon"
		},
		{
			"_id": "I04171219520487091CZmt7K",
			"_tpl": "5dcbd6dddbd3d91b3e5468de",
			"parentId": "I04171229390613807dGFkuL",
			"slotId": "mod_pistol_grip",
			"upd": {
				"SpawnedInSession": true
			}
		},
		{
			"_id": "MagazineWeaponScav9599",
			"_tpl": "5df8f535bb49d91fb446d6b0",
			"parentId": "I04171229390613807dGFkuL",
			"slotId": "mod_magazine",
			"upd": {
				"SpawnedInSession": true
			}
		},
		{
			"_id": "AmmoMag18511",
			"_tpl": "58dd3ad986f77403051cba8f",
			"parentId": "MagazineWeaponScav9599",
			"slotId": "cartridges",
			"upd": {
				"SpawnedInSession": true,
				"StackObjectsCount": 10
			}
		},
		{
			"_id": "I04171218465705479WR3aWC",
			"_tpl": "5dcbd6b46ec07c0c4347a564",
			"parentId": "I04171229390613807dGFkuL",
			"slotId": "mod_handguard",
			"upd": {
				"SpawnedInSession": true
			}
		},
		{
			"_id": "I04171225455608625vOHrLc",
			"_tpl": "5dcbe9431e1f4616d354987e",
			"parentId": "I04171229390613807dGFkuL",
			"slotId": "mod_barrel",
			"upd": {
				"SpawnedInSession": true
			}
		},
		{
			"_id": "I04171228563324203IPCKBP",
			"_tpl": "57adff4f24597737f373b6e6",
			"parentId": "I04171229390613807dGFkuL",
			"slotId": "mod_scope",
			"upd": {
				"SpawnedInSession": true
			}
		},
		{
			"_id": "I0417122375570940419eDFY",
			"_tpl": "57cffb66245977632f391a99",
			"parentId": "I04171218465705479WR3aWC",
			"slotId": "mod_mount_000",
			"upd": {
				"SpawnedInSession": true
			}
		},
		{
			"_id": "I04171225327745257Adjsco",
			"_tpl": "5cdd7693d7f00c0010373aa5",
			"parentId": "I04171225455608625vOHrLc",
			"slotId": "mod_muzzle",
			"upd": {
				"SpawnedInSession": true
			}
		},
		{
			"_id": "I0417122678611253833hbRy",
			"_tpl": "57ae0171245977343c27bfcf",
			"parentId": "I04171228563324203IPCKBP",
			"slotId": "mod_scope",
			"upd": {
				"SpawnedInSession": true
			}
		},
		{
			"_id": "mag0Vest105373",
			"_tpl": "5df8f535bb49d91fb446d6b0",
			"parentId": "TacticalVest399026",
			"slotId": "1",
			"location": {
				"x": 0,
				"y": 1,
				"r": "Horizontal"
			},
			"upd": {
				"SpawnedInSession": true
			}
		},
		{
			"_id": "AmmoMag0Vest189443",
			"_tpl": "58dd3ad986f77403051cba8f",
			"parentId": "mag0Vest105373",
			"slotId": "cartridges",
			"upd": {
				"SpawnedInSession": true,
				"StackObjectsCount": 10
			}
		},
		{
			"_id": "mag3Vest568638",
			"_tpl": "5df8f535bb49d91fb446d6b0",
			"parentId": "TacticalVest399026",
			"slotId": "5",
			"location": {
				"x": 0,
				"y": 1,
				"r": "Horizontal"
			},
			"upd": {
				"SpawnedInSession": true
			}
		},
		{
			"_id": "AmmoMag3Vest957037",
			"_tpl": "5e023e53d4353e3302577c4c",
			"parentId": "mag3Vest568638",
			"slotId": "cartridges",
			"upd": {
				"SpawnedInSession": true,
				"StackObjectsCount": 10
			}
		},
		{
			"_id": "StackAmmo6098179834",
			"_tpl": "5e023e53d4353e3302577c4c",
			"parentId": "TacticalVest399026",
			"slotId": "8",
			"upd": {
				"SpawnedInSession": true,
				"StackObjectsCount": 5
			}
		},
		{
			"_id": "StackAmmo50250441617",
			"_tpl": "5e023e53d4353e3302577c4c",
			"parentId": "TacticalVest399026",
			"slotId": "10",
			"upd": {
				"SpawnedInSession": true,
				"StackObjectsCount": 35
			}
		},
		{
			"_id": "Scabbard7981",
			"_tpl": "5c07df7f0db834001b73588a",
			"parentId": "5c6687d65e9d882c8841f0fd",
			"slotId": "Scabbard",
			"upd": {
				"SpawnedInSession": true
			}
		},
		{
			"_id": "Headwear93477",
			"_tpl": "5e01ef6886f77445f643baa4",
			"parentId": "5c6687d65e9d882c8841f0fd",
			"slotId": "Headwear",
			"upd": {
				"SpawnedInSession": true
			}
		},
		{
			"_id": "Headwear_cover_3883",
			"_tpl": "5e00cfa786f77469dc6e5685",
			"parentId": "Headwear93477",
			"slotId": "mod_equipment_000",
			"upd": {
				"Togglable": {
					"On": true
				}
			}
		},
		{
			"_id": "Backpack555941",
			"_tpl": "5ca20d5986f774331e7c9602",
			"parentId": "5c6687d65e9d882c8841f0fd",
			"slotId": "Backpack",
			"upd": {
				"SpawnedInSession": true
			}
		},
		{
			"_id": "BP_Backpack555941_887716",
			"_tpl": "599851db86f77467372f0a18",
			"parentId": "Backpack555941",
			"slotId": "main",
			"location": {
				"x": 0,
				"y": 0,
				"r": "Horizontal"
			},
			"upd": {
				"SpawnedInSession": true
			}
		},
		{
			"_id": "BP_Backpack555941_507049",
			"_tpl": "5a788068c5856700137e4c8f",
			"parentId": "Backpack555941",
			"slotId": "main",
			"location": {
				"x": 0,
				"y": 1,
				"r": "Horizontal"
			},
			"upd": {
				"SpawnedInSession": true
			}
		},
		{
			"_id": "BP_Backpack555941_895532",
			"_tpl": "587e08ee245977446b4410cf",
			"parentId": "Backpack555941",
			"slotId": "main",
			"location": {
				"x": 0,
				"y": 2,
				"r": "Horizontal"
			},
			"upd": {
				"SpawnedInSession": true
			}
		},
		{
			"_id": "BP_Backpack555941_795063",
			"_tpl": "5b4335ba86f7744d2837a264",
			"parentId": "Backpack555941",
			"slotId": "main",
			"location": {
				"x": 0,
				"y": 3,
				"r": "Horizontal"
			},
			"upd": {
				"SpawnedInSession": true
			}
		},
		{
			"_id": "ArmorVest997096",
			"_tpl": "5c0e51be86f774598e797894",
			"parentId": "5c6687d65e9d882c8841f0fd",
			"slotId": "ArmorVest",
			"upd": {
				"Repairable": {
					"MaxDurability": 47,
					"Durability": 26
				}
			}
		},
		{
			"_id": "Pocket_379717",
			"_tpl": "59e361e886f774176c10a2a5",
			"parentId": "5c6687d65e9d882c8841f121",
			"slotId": "pocket1",
			"location": {
				"x": 0,
				"y": 0,
				"r": "Horizontal"
			},
			"upd": {
				"SpawnedInSession": true
			}
		},
		{
			"_id": "Pocket_14472",
			"_tpl": "5913611c86f77479e0084092",
			"parentId": "5c6687d65e9d882c8841f121",
			"slotId": "pocket2",
			"location": {
				"x": 0,
				"y": 0,
				"r": "Horizontal"
			},
			"upd": {
				"SpawnedInSession": true
			}
		},
		{
			"_id": "Pocket_799664",
			"_tpl": "57347da92459774491567cf5",
			"parentId": "5c6687d65e9d882c8841f121",
			"slotId": "pocket3",
			"location": {
				"x": 0,
				"y": 0,
				"r": "Horizontal"
			},
			"upd": {
				"SpawnedInSession": true
			}
		}
	],
	"equipment": "5c6687d65e9d882c8841f0fd",
	"stash": "5c6687d65e9d882c8841f0fc",
	"questRaidItems": "5c6687d65e9d882c8841f0fe",
	"questStashItems": "5c6687d65e9d882c8841f0ff",
	"fastPanel": {}
}