{
	"items": [
		{
			"_id": "5c6687d65e9d882c8841f0fd",
			"_tpl": "55d7217a4bdc2d86028b456d"
		},
		{
			"_id": "5c6687d65e9d882c8841f121",
			"_tpl": "557ffd194bdc2d28148b457f",
			"parentId": "5c6687d65e9d882c8841f0fd",
			"slotId": "Pockets"
		},
		{
			"_id": "5c6687d65e9d882c8841f0fc",
			"_tpl": "566abbc34bdc2d92178b4576"
		},
		{
			"_id": "5c6687d65e9d882c8841f0ff",
			"_tpl": "5963866b86f7747bfa1c4462"
		},
		{
			"_id": "5c6687d65e9d882c8841f0fe",
			"_tpl": "5963866286f7747bf429b572"
		},
		{
			"_id": "TacticalVest767762",
			"_tpl": "5ca20abf86f77418567a43f2",
			"parentId": "5c6687d65e9d882c8841f0fd",
			"slotId": "TacticalVest",
			"upd": {
				"SpawnedInSession": true
			}
		},
		{
			"_id": "dcvOD03bNUlhUr72CxFgjvhJxM2s",
			"_tpl": "5dcbd56fdbd3d91b3e5468d5",
			"parentId": "5c6687d65e9d882c8841f0fd",
			"slotId": "FirstPrimaryWeapon"
		},
		{
			"_id": "I0417367817763289BnrX7FX",
			"_tpl": "5c48a2c22e221602b313fb6c",
			"parentId": "I04173114082335223aCMoO4",
			"slotId": "mod_pistol_grip",
			"upd": {
				"SpawnedInSession": true
			}
		},
		{
			"_id": "MagazineWeaponScav9142",
			"_tpl": "5a3501acc4a282000d72293a",
			"parentId": "dcvOD03bNUlhUr72CxFgjvhJxM2s",
			"slotId": "mod_magazine",
			"upd": {
				"SpawnedInSession": true
			}
		},
		{
			"_id": "AmmoMag15672",
			"_tpl": "5e023e6e34d52a55c3304f71",
			"parentId": "MagazineWeaponScav9142",
			"slotId": "cartridges",
			"upd": {
				"SpawnedInSession": true,
				"StackObjectsCount": 20
			}
		},
		{
			"_id": "I0417362050658591WLneXJe",
			"_tpl": "5c48a14f2e2216152006edd7",
			"parentId": "I04173114082335223aCMoO4",
			"slotId": "mod_handguard",
			"upd": {
				"SpawnedInSession": true
			}
		},
		{
			"_id": "I0417365888338202epZefGB",
			"_tpl": "5c07dd120db834001c39092d",
			"parentId": "I04173114082335223aCMoO4",
			"slotId": "mod_scope",
			"upd": {
				"SpawnedInSession": true
			}
		},
		{
			"_id": "I04173645802307203eru5Ii",
			"_tpl": "5cdd7685d7f00c000f260ed2",
			"parentId": "I04173117000928737A2962h",
			"slotId": "mod_muzzle",
			"upd": {
				"SpawnedInSession": true
			}
		},
		{
			"_id": "I04173117000928737A2962h",
			"_tpl": "5dcbe9431e1f4616d354987e",
			"parentId": "I04173114082335223aCMoO4",
			"slotId": "mod_barrel",
			"upd": {
				"SpawnedInSession": true
			}
		},
		{
			"_id": "I04173117579018270UTkYP0",
			"_tpl": "57cffb66245977632f391a99",
			"parentId": "I0417362050658591WLneXJe",
			"slotId": "mod_mount_000",
			"upd": {
				"SpawnedInSession": true
			}
		},
		{
			"_id": "mag1Vest863958",
			"_tpl": "5a3501acc4a282000d72293a",
			"parentId": "TacticalVest767762",
			"slotId": "2",
			"location": {
				"x": 0,
				"y": 0,
				"r": "Horizontal"
			},
			"upd": {
				"SpawnedInSession": true
			}
		},
		{
			"_id": "AmmoMag1Vest373005",
			"_tpl": "5a6086ea4f39f99cd479502f",
			"parentId": "mag1Vest863958",
			"slotId": "cartridges",
			"upd": {
				"SpawnedInSession": true,
				"StackObjectsCount": 20
			}
		},
		{
			"_id": "mag2Vest211379",
			"_tpl": "5a3501acc4a282000d72293a",
			"parentId": "TacticalVest767762",
			"slotId": "4",
			"location": {
				"x": 0,
				"y": 0,
				"r": "Horizontal"
			},
			"upd": {
				"SpawnedInSession": true
			}
		},
		{
			"_id": "AmmoMag2Vest850829",
			"_tpl": "5a6086ea4f39f99cd479502f",
			"parentId": "mag2Vest211379",
			"slotId": "cartridges",
			"upd": {
				"SpawnedInSession": true,
				"StackObjectsCount": 20
			}
		},
		{
			"_id": "mag3Vest646820",
			"_tpl": "5a3501acc4a282000d72293a",
			"parentId": "TacticalVest767762",
			"slotId": "6",
			"location": {
				"x": 0,
				"y": 0,
				"r": "Horizontal"
			},
			"upd": {
				"SpawnedInSession": true
			}
		},
		{
			"_id": "AmmoMag3Vest480651",
			"_tpl": "5e023e53d4353e3302577c4c",
			"parentId": "mag3Vest646820",
			"slotId": "cartridges",
			"upd": {
				"SpawnedInSession": true,
				"StackObjectsCount": 20
			}
		},
		{
			"_id": "Scabbard182701",
			"_tpl": "54491bb74bdc2d09088b4567",
			"parentId": "5c6687d65e9d882c8841f0fd",
			"slotId": "Scabbard",
			"upd": {
				"SpawnedInSession": true
			}
		},
		{
			"_id": "Headwear49213",
			"_tpl": "5ca20ee186f774799474abc2",
			"parentId": "5c6687d65e9d882c8841f0fd",
			"slotId": "Headwear",
			"upd": {
				"SpawnedInSession": true
			}
		},
		{
			"_id": "Headwear_cover_9765",
			"_tpl": "5ca2113f86f7740b2547e1d2",
			"parentId": "Headwear49213",
			"slotId": "mod_equipment",
			"upd": {
				"Togglable": {
					"On": true
				}
			}
		},
		{
			"_id": "Eyewear820672",
			"_tpl": "59e770b986f7742cbd762754",
			"parentId": "5c6687d65e9d882c8841f0fd",
			"slotId": "Eyewear",
			"upd": {
				"SpawnedInSession": true
			}
		},
		{
			"_id": "FaceCover744071",
			"_tpl": "5b4326435acfc433000ed01d",
			"parentId": "5c6687d65e9d882c8841f0fd",
			"slotId": "FaceCover",
			"upd": {
				"SpawnedInSession": true
			}
		},
		{
			"_id": "Backpack378446",
			"_tpl": "5ca20d5986f774331e7c9602",
			"parentId": "5c6687d65e9d882c8841f0fd",
			"slotId": "Backpack",
			"upd": {
				"SpawnedInSession": true
			}
		},
		{
			"_id": "BP_Backpack378446_624022",
			"_tpl": "5d00ef6dd7ad1a0940739b16",
			"parentId": "Backpack378446",
			"slotId": "main",
			"location": {
				"x": 0,
				"y": 0,
				"r": "Horizontal"
			},
			"upd": {
				"SpawnedInSession": true
			}
		}
	],
	"equipment": "5c6687d65e9d882c8841f0fd",
	"stash": "5c6687d65e9d882c8841f0fc",
	"questRaidItems": "5c6687d65e9d882c8841f0fe",
	"questStashItems": "5c6687d65e9d882c8841f0ff",
	"fastPanel": {}
}