{
	"items": [
		{
			"_id": "5c6687d65e9d882c8841f0fd",
			"_tpl": "55d7217a4bdc2d86028b456d"
		},
		{
			"_id": "5c6687d65e9d882c8841f121",
			"_tpl": "557ffd194bdc2d28148b457f",
			"parentId": "5c6687d65e9d882c8841f0fd",
			"slotId": "Pockets"
		},
		{
			"_id": "5c6687d65e9d882c8841f0fc",
			"_tpl": "566abbc34bdc2d92178b4576"
		},
		{
			"_id": "5c6687d65e9d882c8841f0ff",
			"_tpl": "5963866b86f7747bfa1c4462"
		},
		{
			"_id": "5c6687d65e9d882c8841f0fe",
			"_tpl": "5963866286f7747bf429b572"
		},
		{
			"_id": "TacticalVest811221",
			"_tpl": "5ab8dced86f774646209ec87",
			"parentId": "5c6687d65e9d882c8841f0fd",
			"slotId": "TacticalVest",
			"upd": {
				"SpawnedInSession": true
			}
		},
		{
			"_id": "I041619386303781499JNf0S",
			"_tpl": "5c07c60e0db834002330051f",
			"parentId": "5c6687d65e9d882c8841f0fd",
			"slotId": "FirstPrimaryWeapon"
		},
		{
			"_id": "5df7b9abef12bf7a252437a0",
			"_tpl": "557ffd194bdc2d28148b457f",
			"parentId": "5df7b9abef12bf7a252437a1",
			"slotId": "Pockets"
		},
		{
			"_id": "I041619373961130039jLlaK",
			"_tpl": "59db3a1d86f77429e05b4e92",
			"parentId": "I041619386303781499JNf0S",
			"slotId": "mod_pistol_grip",
			"upd": {
				"SpawnedInSession": true
			}
		},
		{
			"_id": "MagazineWeaponScav8144",
			"_tpl": "544a37c44bdc2d25388b4567",
			"parentId": "I041619386303781499JNf0S",
			"slotId": "mod_magazine",
			"upd": {
				"SpawnedInSession": true
			}
		},
		{
			"_id": "AmmoMag1849",
			"_tpl": "59e6906286f7746c9f75e847",
			"parentId": "MagazineWeaponScav8144",
			"slotId": "cartridges",
			"upd": {
				"SpawnedInSession": true,
				"StackObjectsCount": 60
			}
		},
		{
			"_id": "I041619378857297849UhoZc",
			"_tpl": "59bfe68886f7746004266202",
			"parentId": "I041619386303781499JNf0S",
			"slotId": "mod_reciever",
			"upd": {
				"SpawnedInSession": true
			}
		},
		{
			"_id": "I041619378269490185dv1TR",
			"_tpl": "5d120a10d7ad1a4e1026ba85",
			"parentId": "I041619386303781499JNf0S",
			"slotId": "mod_stock",
			"upd": {
				"SpawnedInSession": true
			}
		},
		{
			"_id": "I041619376329390834ZX05E",
			"_tpl": "5c0faf68d174af02a96260b8",
			"parentId": "I041619386303781499JNf0S",
			"slotId": "mod_charge",
			"upd": {
				"SpawnedInSession": true
			}
		},
		{
			"_id": "I041619387375461684ar5AL",
			"_tpl": "5d1b5e94d7ad1a2b865a96b0",
			"parentId": "I041619378857297849UhoZc",
			"slotId": "mod_scope",
			"upd": {
				"SpawnedInSession": true
			}
		},
		{
			"_id": "I041619387464515711Fpnda",
			"_tpl": "5d440b9fa4b93601354d480c",
			"parentId": "I041619378857297849UhoZc",
			"slotId": "mod_barrel",
			"upd": {
				"SpawnedInSession": true
			}
		},
		{
			"_id": "I041619386442120693Ppo5I",
			"_tpl": "595cfa8b86f77427437e845b",
			"parentId": "I041619378857297849UhoZc",
			"slotId": "mod_handguard",
			"upd": {
				"SpawnedInSession": true
			}
		},
		{
			"_id": "I041619382139649452cqRmY",
			"_tpl": "5c7e5f112e221600106f4ede",
			"parentId": "I041619387464515711Fpnda",
			"slotId": "mod_muzzle",
			"upd": {
				"SpawnedInSession": true
			}
		},
		{
			"_id": "I041619385553870924iWfQI",
			"_tpl": "5d00ec68d7ad1a04a067e5be",
			"parentId": "I041619387464515711Fpnda",
			"slotId": "mod_gas_block",
			"upd": {
				"SpawnedInSession": true
			}
		},
		{
			"_id": "I041619386826026938fzE8h",
			"_tpl": "5a34fe59c4a282000b1521a2",
			"parentId": "I041619382139649452cqRmY",
			"slotId": "mod_muzzle",
			"upd": {
				"SpawnedInSession": true
			}
		},
		{
			"_id": "I041619386696266962TTk9p",
			"_tpl": "59e0bed186f774156f04ce84",
			"parentId": "I041619386442120693Ppo5I",
			"slotId": "mod_mount_000",
			"upd": {
				"SpawnedInSession": true
			}
		},
		{
			"_id": "I0416193855950526299I4y3",
			"_tpl": "5a7dbfc1159bd40016548fde",
			"parentId": "I041619386696266962TTk9p",
			"slotId": "mod_foregrip",
			"upd": {
				"SpawnedInSession": true
			}
		},
		{
			"_id": "I041619384526017728MEVGz",
			"_tpl": "5d120a28d7ad1a1c8962e295",
			"parentId": "I041619378269490185dv1TR",
			"slotId": "mod_stock",
			"upd": {
				"SpawnedInSession": true
			}
		},
		{
			"_id": "mag0Vest86284",
			"_tpl": "5c6d450c2e221600114c997d",
			"parentId": "TacticalVest811221",
			"slotId": "1",
			"location": {
				"x": 0,
				"y": 0,
				"r": "Horizontal"
			},
			"upd": {
				"SpawnedInSession": true
			}
		},
		{
			"_id": "AmmoMag0Vest366783",
			"_tpl": "59e6918f86f7746c9f75e849",
			"parentId": "mag0Vest86284",
			"slotId": "cartridges",
			"upd": {
				"SpawnedInSession": true,
				"StackObjectsCount": 30
			}
		},
		{
			"_id": "mag2Vest273820",
			"_tpl": "5c6d450c2e221600114c997d",
			"parentId": "TacticalVest811221",
			"slotId": "4",
			"location": {
				"x": 0,
				"y": 0,
				"r": "Horizontal"
			},
			"upd": {
				"SpawnedInSession": true
			}
		},
		{
			"_id": "AmmoMag2Vest692547",
			"_tpl": "59e6927d86f77411da468256",
			"parentId": "mag2Vest273820",
			"slotId": "cartridges",
			"upd": {
				"SpawnedInSession": true,
				"StackObjectsCount": 30
			}
		},
		{
			"_id": "mag3Vest323682",
			"_tpl": "5c6d450c2e221600114c997d",
			"parentId": "TacticalVest811221",
			"slotId": "6",
			"location": {
				"x": 0,
				"y": 0,
				"r": "Horizontal"
			},
			"upd": {
				"SpawnedInSession": true
			}
		},
		{
			"_id": "AmmoMag3Vest782141",
			"_tpl": "5c0d5ae286f7741e46554302",
			"parentId": "mag3Vest323682",
			"slotId": "cartridges",
			"upd": {
				"SpawnedInSession": true,
				"StackObjectsCount": 30
			}
		},
		{
			"_id": "Scabbard981090",
			"_tpl": "57cd379a24597778e7682ecf",
			"parentId": "5c6687d65e9d882c8841f0fd",
			"slotId": "Scabbard",
			"upd": {
				"SpawnedInSession": true
			}
		},
		{
			"_id": "Headwear217948",
			"_tpl": "5b40e5e25acfc4001a599bea",
			"parentId": "5c6687d65e9d882c8841f0fd",
			"slotId": "Headwear",
			"upd": {
				"SpawnedInSession": true
			}
		},
		{
			"_id": "Eyewear524191",
			"_tpl": "5d6d2ef3a4b93618084f58bd",
			"parentId": "5c6687d65e9d882c8841f0fd",
			"slotId": "Eyewear",
			"upd": {
				"SpawnedInSession": true
			}
		},
		{
			"_id": "FaceCover170403",
			"_tpl": "5b4326435acfc433000ed01d",
			"parentId": "5c6687d65e9d882c8841f0fd",
			"slotId": "FaceCover",
			"upd": {
				"SpawnedInSession": true
			}
		},
		{
			"_id": "Backpack307035",
			"_tpl": "56e335e4d2720b6c058b456d",
			"parentId": "5c6687d65e9d882c8841f0fd",
			"slotId": "Backpack",
			"upd": {
				"SpawnedInSession": true
			}
		},
		{
			"_id": "BP_Backpack307035_598212",
			"_tpl": "5bc9b156d4351e00367fbce9",
			"parentId": "Backpack307035",
			"slotId": "main",
			"location": {
				"x": 0,
				"y": 0,
				"r": "Horizontal"
			},
			"upd": {
				"SpawnedInSession": true
			}
		},
		{
			"_id": "BP_Backpack307035_529292",
			"_tpl": "57616ca52459773c69055192",
			"parentId": "Backpack307035",
			"slotId": "main",
			"location": {
				"x": 0,
				"y": 1,
				"r": "Horizontal"
			},
			"upd": {
				"SpawnedInSession": true
			}
		},
		{
			"_id": "BP_Backpack307035_729100",
			"_tpl": "5926d40686f7740f152b6b7e",
			"parentId": "Backpack307035",
			"slotId": "main",
			"location": {
				"x": 0,
				"y": 2,
				"r": "Horizontal"
			},
			"upd": {
				"SpawnedInSession": true
			}
		},
		{
			"_id": "BP_Backpack307035_177711",
			"_tpl": "59faf98186f774067b6be103",
			"parentId": "Backpack307035",
			"slotId": "main",
			"location": {
				"x": 0,
				"y": 3,
				"r": "Horizontal"
			},
			"upd": {
				"SpawnedInSession": true
			}
		},
		{
			"_id": "BP_Backpack307035_122228",
			"_tpl": "590c5f0d86f77413997acfab",
			"parentId": "Backpack307035",
			"slotId": "main",
			"location": {
				"x": 1,
				"y": 3,
				"r": "Horizontal"
			},
			"upd": {
				"SpawnedInSession": true
			}
		},
		{
			"_id": "BP_Backpack307035_286561",
			"_tpl": "593aa4be86f77457f56379f8",
			"parentId": "Backpack307035",
			"slotId": "main",
			"location": {
				"x": 1,
				"y": 0,
				"r": "Horizontal"
			},
			"upd": {
				"SpawnedInSession": true
			}
		},
		{
			"_id": "BP_Backpack307035_788323",
			"_tpl": "5bc9bdb8d4351e003562b8a1",
			"parentId": "Backpack307035",
			"slotId": "main",
			"location": {
				"x": 2,
				"y": 0,
				"r": "Horizontal"
			},
			"upd": {
				"SpawnedInSession": true
			}
		},
		{
			"_id": "BP_Backpack307035_927992",
			"_tpl": "5a16b93dfcdbcbcae6687261",
			"parentId": "Backpack307035",
			"slotId": "main",
			"location": {
				"x": 2,
				"y": 1,
				"r": "Horizontal"
			},
			"upd": {
				"SpawnedInSession": true
			}
		},
		{
			"_id": "BP_Backpack307035_520800",
			"_tpl": "5d1b3a5d86f774252167ba22",
			"parentId": "Backpack307035",
			"slotId": "main",
			"location": {
				"x": 2,
				"y": 2,
				"r": "Horizontal"
			},
			"upd": {
				"SpawnedInSession": true
			}
		},
		{
			"_id": "BP_Backpack307035_301054",
			"_tpl": "59e3577886f774176a362503",
			"parentId": "Backpack307035",
			"slotId": "main",
			"location": {
				"x": 2,
				"y": 3,
				"r": "Horizontal"
			},
			"upd": {
				"SpawnedInSession": true
			}
		},
		{
			"_id": "ArmorVest411206",
			"_tpl": "5c0e51be86f774598e797894",
			"parentId": "5c6687d65e9d882c8841f0fd",
			"slotId": "ArmorVest",
			"upd": {
				"Repairable": {
					"MaxDurability": 47,
					"Durability": 21
				}
			}
		},
		{
			"_id": "Pocket_511399",
			"_tpl": "573477e124597737dd42e191",
			"parentId": "5c6687d65e9d882c8841f121",
			"slotId": "pocket1",
			"location": {
				"x": 0,
				"y": 0,
				"r": "Horizontal"
			},
			"upd": {
				"SpawnedInSession": true
			}
		},
		{
			"_id": "Pocket_483242",
			"_tpl": "5bc9b355d4351e6d1509862a",
			"parentId": "5c6687d65e9d882c8841f121",
			"slotId": "pocket2",
			"location": {
				"x": 0,
				"y": 0,
				"r": "Horizontal"
			},
			"upd": {
				"SpawnedInSession": true
			}
		},
		{
			"_id": "Pocket_223297",
			"_tpl": "57347d692459774491567cf1",
			"parentId": "5c6687d65e9d882c8841f121",
			"slotId": "pocket3",
			"location": {
				"x": 0,
				"y": 0,
				"r": "Horizontal"
			},
			"upd": {
				"SpawnedInSession": true
			}
		}
	],
	"equipment": "5c6687d65e9d882c8841f0fd",
	"stash": "5c6687d65e9d882c8841f0fc",
	"questRaidItems": "5c6687d65e9d882c8841f0fe",
	"questStashItems": "5c6687d65e9d882c8841f0ff",
	"fastPanel": {}
}