{
	"items": [
		{
			"_id": "5c6687d65e9d882c8841f0fd",
			"_tpl": "55d7217a4bdc2d86028b456d"
		},
		{
			"_id": "5c6687d65e9d882c8841f121",
			"_tpl": "557ffd194bdc2d28148b457f",
			"parentId": "5c6687d65e9d882c8841f0fd",
			"slotId": "Pockets"
		},
		{
			"_id": "5c6687d65e9d882c8841f0fc",
			"_tpl": "566abbc34bdc2d92178b4576"
		},
		{
			"_id": "5c6687d65e9d882c8841f0ff",
			"_tpl": "5963866b86f7747bfa1c4462"
		},
		{
			"_id": "5c6687d65e9d882c8841f0fe",
			"_tpl": "5963866286f7747bf429b572"
		},
		{
			"_id": "TacticalVest214771",
			"_tpl": "5c0e3eb886f7742015526062",
			"parentId": "5c6687d65e9d882c8841f0fd",
			"slotId": "TacticalVest",
			"upd": {
				"SpawnedInSession": true
			}
		},
		{
			"_id": "58db769986f77474ad53a9f2",
			"_tpl": "574d967124597745970e7c94",
			"parentId": "5c6687d65e9d882c8841f0fd",
			"slotId": "FirstPrimaryWeapon"
		},
		{
			"_id": "58db769986f77474ad53a9f3",
			"_tpl": "574dad8024597745964bf05c",
			"parentId": "58db769986f77474ad53a9f2",
			"slotId": "mod_stock",
			"upd": {
				"SpawnedInSession": true
			}
		},
		{
			"_id": "58db769986f77474ad53a9f4",
			"_tpl": "574db213245977459a2f3f5d",
			"parentId": "58db769986f77474ad53a9f2",
			"slotId": "mod_sight_rear",
			"upd": {
				"SpawnedInSession": true
			}
		},
		{
			"_id": "MagazineWeaponScav9854",
			"_tpl": "587df583245977373c4f1129",
			"parentId": "58db769986f77474ad53a9f2",
			"slotId": "mod_magazine",
			"upd": {
				"SpawnedInSession": true
			}
		},
		{
			"_id": "AmmoMag12663",
			"_tpl": "59e0d99486f7744a32234762",
			"parentId": "MagazineWeaponScav9854",
			"slotId": "cartridges",
			"upd": {
				"SpawnedInSession": true,
				"StackObjectsCount": 20
			}
		},
		{
			"_id": "mag3Vest296596",
			"_tpl": "5c5970672e221602b21d7855",
			"parentId": "TacticalVest214771",
			"slotId": "4",
			"location": {
				"x": 0,
				"y": 0,
				"r": "Horizontal"
			},
			"upd": {
				"SpawnedInSession": true
			}
		},
		{
			"_id": "AmmoMag3Vest666386",
			"_tpl": "59e4d24686f7741776641ac7",
			"parentId": "mag3Vest296596",
			"slotId": "cartridges",
			"upd": {
				"SpawnedInSession": true,
				"StackObjectsCount": 35
			}
		},
		{
			"_id": "Scabbard17079",
			"_tpl": "54491bb74bdc2d09088b4567",
			"parentId": "5c6687d65e9d882c8841f0fd",
			"slotId": "Scabbard",
			"upd": {
				"SpawnedInSession": true
			}
		},
		{
			"_id": "Headwear312936",
			"_tpl": "5b40e61f5acfc4001a599bec",
			"parentId": "5c6687d65e9d882c8841f0fd",
			"slotId": "Headwear",
			"upd": {
				"SpawnedInSession": true
			}
		},
		{
			"_id": "Backpack451446",
			"_tpl": "544a5cde4bdc2d39388b456b",
			"parentId": "5c6687d65e9d882c8841f0fd",
			"slotId": "Backpack",
			"upd": {
				"SpawnedInSession": true
			}
		},
		{
			"_id": "BP_Backpack451446_594663",
			"_tpl": "57ffa9f4245977728561e844",
			"parentId": "Backpack451446",
			"slotId": "main",
			"location": {
				"x": 0,
				"y": 0,
				"r": "Horizontal"
			},
			"upd": {
				"SpawnedInSession": true
			}
		},
		{
			"_id": "BP_Backpack451446_406541",
			"_tpl": "59e358a886f7741776641ac3",
			"parentId": "Backpack451446",
			"slotId": "main",
			"location": {
				"x": 0,
				"y": 1,
				"r": "Horizontal"
			},
			"upd": {
				"SpawnedInSession": true
			}
		},
		{
			"_id": "BP_Backpack451446_287156",
			"_tpl": "5bb20e58d4351e00320205d7",
			"parentId": "Backpack451446",
			"slotId": "main",
			"location": {
				"x": 0,
				"y": 3,
				"r": "Horizontal"
			},
			"upd": {
				"SpawnedInSession": true
			}
		},
		{
			"_id": "BP_Backpack451446_412548",
			"_tpl": "5a71e4f48dc32e001207fb26",
			"parentId": "Backpack451446",
			"slotId": "main",
			"location": {
				"x": 1,
				"y": 0,
				"r": "Horizontal"
			},
			"upd": {
				"SpawnedInSession": true
			}
		},
		{
			"_id": "BP_Backpack451446_959179",
			"_tpl": "5a71e4f48dc32e001207fb26",
			"parentId": "Backpack451446",
			"slotId": "main",
			"location": {
				"x": 1,
				"y": 1,
				"r": "Horizontal"
			},
			"upd": {
				"SpawnedInSession": true
			}
		},
		{
			"_id": "ArmorVest299153",
			"_tpl": "5c0e5edb86f77461f55ed1f7",
			"parentId": "5c6687d65e9d882c8841f0fd",
			"slotId": "ArmorVest",
			"upd": {
				"Repairable": {
					"MaxDurability": 50,
					"Durability": 6
				}
			}
		},
		{
			"_id": "Pocket_601569",
			"_tpl": "544fb5454bdc2df8738b456a",
			"parentId": "5c6687d65e9d882c8841f121",
			"slotId": "pocket1",
			"location": {
				"x": 0,
				"y": 0,
				"r": "Horizontal"
			},
			"upd": {
				"SpawnedInSession": true
			}
		},
		{
			"_id": "Pocket_213164",
			"_tpl": "591383f186f7744a4c5edcf3",
			"parentId": "5c6687d65e9d882c8841f121",
			"slotId": "pocket2",
			"location": {
				"x": 0,
				"y": 0,
				"r": "Horizontal"
			},
			"upd": {
				"SpawnedInSession": true
			}
		},
		{
			"_id": "Pocket_235929",
			"_tpl": "59148f8286f7741b951ea113",
			"parentId": "5c6687d65e9d882c8841f121",
			"slotId": "pocket3",
			"location": {
				"x": 0,
				"y": 0,
				"r": "Horizontal"
			},
			"upd": {
				"SpawnedInSession": true
			}
		}
	],
	"equipment": "5c6687d65e9d882c8841f0fd",
	"stash": "5c6687d65e9d882c8841f0fc",
	"questRaidItems": "5c6687d65e9d882c8841f0fe",
	"questStashItems": "5c6687d65e9d882c8841f0ff",
	"fastPanel": {}
}