{
	"items": [
		{
			"_id": "5c6687d65e9d882c8841f0fd",
			"_tpl": "55d7217a4bdc2d86028b456d"
		},
		{
			"_id": "5c6687d65e9d882c8841f121",
			"_tpl": "557ffd194bdc2d28148b457f",
			"parentId": "5c6687d65e9d882c8841f0fd",
			"slotId": "Pockets"
		},
		{
			"_id": "5c6687d65e9d882c8841f0fc",
			"_tpl": "566abbc34bdc2d92178b4576"
		},
		{
			"_id": "5c6687d65e9d882c8841f0ff",
			"_tpl": "5963866b86f7747bfa1c4462"
		},
		{
			"_id": "5c6687d65e9d882c8841f0fe",
			"_tpl": "5963866286f7747bf429b572"
		},
		{
			"_id": "TacticalVest239486",
			"_tpl": "5d5d646386f7742797261fd9",
			"parentId": "5c6687d65e9d882c8841f0fd",
			"slotId": "TacticalVest",
			"upd": {
				"SpawnedInSession": true
			}
		},
		{
			"_id": "5b439b7486f7744fd8059cd8",
			"_tpl": "574d967124597745970e7c94",
			"parentId": "5c6687d65e9d882c8841f0fd",
			"slotId": "FirstPrimaryWeapon"
		},
		{
			"_id": "5b439b7486f7744fd8059cd9",
			"_tpl": "5afd7ded5acfc40017541f5e",
			"parentId": "5b439b7486f7744fd8059cd8",
			"slotId": "mod_stock",
			"upd": {
				"SpawnedInSession": true
			}
		},
		{
			"_id": "5b439b7486f7744fd8059cda",
			"_tpl": "5afd7e095acfc40017541f61",
			"parentId": "5b439b7486f7744fd8059cd9",
			"slotId": "mod_stock",
			"upd": {
				"SpawnedInSession": true
			}
		},
		{
			"_id": "5b439b7486f7744fd8059cdb",
			"_tpl": "55d4ae6c4bdc2d8b2f8b456e",
			"parentId": "5b439b7486f7744fd8059cda",
			"slotId": "mod_stock",
			"upd": {
				"SpawnedInSession": true
			}
		},
		{
			"_id": "5b439b7486f7744fd8059cdc",
			"_tpl": "5afd7e445acfc4001637e35a",
			"parentId": "5b439b7486f7744fd8059cd9",
			"slotId": "mod_pistol_grip",
			"upd": {
				"SpawnedInSession": true
			}
		},
		{
			"_id": "5b439b7486f7744fd8059cdd",
			"_tpl": "574db213245977459a2f3f5d",
			"parentId": "5b439b7486f7744fd8059cd8",
			"slotId": "mod_sight_rear",
			"upd": {
				"SpawnedInSession": true
			}
		},
		{
			"_id": "MagazineWeaponScav500",
			"_tpl": "587df583245977373c4f1129",
			"parentId": "5b439b7486f7744fd8059cd8",
			"slotId": "mod_magazine",
			"upd": {
				"SpawnedInSession": true
			}
		},
		{
			"_id": "AmmoMag11264",
			"_tpl": "59e4d24686f7741776641ac7",
			"parentId": "MagazineWeaponScav500",
			"slotId": "cartridges",
			"upd": {
				"SpawnedInSession": true,
				"StackObjectsCount": 20
			}
		},
		{
			"_id": "mag0Vest265633",
			"_tpl": "587df583245977373c4f1129",
			"parentId": "TacticalVest239486",
			"slotId": "3",
			"location": {
				"x": 0,
				"y": 0,
				"r": "Horizontal"
			},
			"upd": {
				"SpawnedInSession": true
			}
		},
		{
			"_id": "AmmoMag0Vest214896",
			"_tpl": "59e4d24686f7741776641ac7",
			"parentId": "mag0Vest265633",
			"slotId": "cartridges",
			"upd": {
				"SpawnedInSession": true,
				"StackObjectsCount": 20
			}
		},
		{
			"_id": "mag2Vest608716",
			"_tpl": "587df583245977373c4f1129",
			"parentId": "TacticalVest239486",
			"slotId": "6",
			"location": {
				"x": 0,
				"y": 0,
				"r": "Horizontal"
			},
			"upd": {
				"SpawnedInSession": true
			}
		},
		{
			"_id": "AmmoMag2Vest111291",
			"_tpl": "59e0d99486f7744a32234762",
			"parentId": "mag2Vest608716",
			"slotId": "cartridges",
			"upd": {
				"SpawnedInSession": true,
				"StackObjectsCount": 20
			}
		},
		{
			"_id": "Scabbard415870",
			"_tpl": "57e26ea924597715ca604a09",
			"parentId": "5c6687d65e9d882c8841f0fd",
			"slotId": "Scabbard",
			"upd": {
				"SpawnedInSession": true
			}
		},
		{
			"_id": "Headwear150996",
			"_tpl": "5a43943586f77416ad2f06e2",
			"parentId": "5c6687d65e9d882c8841f0fd",
			"slotId": "Headwear",
			"upd": {
				"SpawnedInSession": true
			}
		},
		{
			"_id": "FaceCover764609",
			"_tpl": "572b7fa524597762b747ce82",
			"parentId": "5c6687d65e9d882c8841f0fd",
			"slotId": "FaceCover",
			"upd": {
				"SpawnedInSession": true
			}
		},
		{
			"_id": "Backpack905733",
			"_tpl": "5ab8ee7786f7742d8f33f0b9",
			"parentId": "5c6687d65e9d882c8841f0fd",
			"slotId": "Backpack",
			"upd": {
				"SpawnedInSession": true
			}
		},
		{
			"_id": "BP_Backpack905733_781146",
			"_tpl": "5c4eecde2e221602b3140418",
			"parentId": "Backpack905733",
			"slotId": "main",
			"location": {
				"x": 0,
				"y": 0,
				"r": "Horizontal"
			},
			"upd": {
				"SpawnedInSession": true
			}
		},
		{
			"_id": "BP_Backpack905733_264728",
			"_tpl": "5649ae4a4bdc2d1b2b8b4588",
			"parentId": "Backpack905733",
			"slotId": "main",
			"location": {
				"x": 0,
				"y": 1,
				"r": "Horizontal"
			},
			"upd": {
				"SpawnedInSession": true
			}
		},
		{
			"_id": "BP_Backpack905733_915543",
			"_tpl": "5b099a765acfc47a8607efe3",
			"parentId": "Backpack905733",
			"slotId": "main",
			"location": {
				"x": 1,
				"y": 0,
				"r": "Horizontal"
			},
			"upd": {
				"SpawnedInSession": true
			}
		},
		{
			"_id": "ArmorVest934335",
			"_tpl": "5c0e625a86f7742d77340f62",
			"parentId": "5c6687d65e9d882c8841f0fd",
			"slotId": "ArmorVest",
			"upd": {
				"Repairable": {
					"MaxDurability": 75,
					"Durability": 30
				}
			}
		},
		{
			"_id": "Pocket_251189",
			"_tpl": "5a0eb6ac86f7743124037a28",
			"parentId": "5c6687d65e9d882c8841f121",
			"slotId": "pocket1",
			"location": {
				"x": 0,
				"y": 0,
				"r": "Horizontal"
			},
			"upd": {
				"SpawnedInSession": true
			}
		}
	],
	"equipment": "5c6687d65e9d882c8841f0fd",
	"stash": "5c6687d65e9d882c8841f0fc",
	"questRaidItems": "5c6687d65e9d882c8841f0fe",
	"questStashItems": "5c6687d65e9d882c8841f0ff",
	"fastPanel": {}
}