{
	"items": [
		{
			"_id": "5c6687d65e9d882c8841f0fd",
			"_tpl": "55d7217a4bdc2d86028b456d"
		},
		{
			"_id": "5c6687d65e9d882c8841f121",
			"_tpl": "557ffd194bdc2d28148b457f",
			"parentId": "5c6687d65e9d882c8841f0fd",
			"slotId": "Pockets"
		},
		{
			"_id": "5c6687d65e9d882c8841f0fc",
			"_tpl": "566abbc34bdc2d92178b4576"
		},
		{
			"_id": "5c6687d65e9d882c8841f0ff",
			"_tpl": "5963866b86f7747bfa1c4462"
		},
		{
			"_id": "5c6687d65e9d882c8841f0fe",
			"_tpl": "5963866286f7747bf429b572"
		},
		{
			"_id": "TacticalVest689194",
			"_tpl": "5c0e9f2c86f77432297fe0a3",
			"parentId": "5c6687d65e9d882c8841f0fd",
			"slotId": "TacticalVest",
			"upd": {
				"SpawnedInSession": true
			}
		},
		{
			"_id": "58db769986f77474ad53a9f2",
			"_tpl": "574d967124597745970e7c94",
			"parentId": "5c6687d65e9d882c8841f0fd",
			"slotId": "FirstPrimaryWeapon"
		},
		{
			"_id": "58db769986f77474ad53a9f3",
			"_tpl": "574dad8024597745964bf05c",
			"parentId": "58db769986f77474ad53a9f2",
			"slotId": "mod_stock",
			"upd": {
				"SpawnedInSession": true
			}
		},
		{
			"_id": "58db769986f77474ad53a9f4",
			"_tpl": "574db213245977459a2f3f5d",
			"parentId": "58db769986f77474ad53a9f2",
			"slotId": "mod_sight_rear",
			"upd": {
				"SpawnedInSession": true
			}
		},
		{
			"_id": "MagazineWeaponScav6668",
			"_tpl": "587df583245977373c4f1129",
			"parentId": "58db769986f77474ad53a9f2",
			"slotId": "mod_magazine",
			"upd": {
				"SpawnedInSession": true
			}
		},
		{
			"_id": "AmmoMag13195",
			"_tpl": "59e4d24686f7741776641ac7",
			"parentId": "MagazineWeaponScav6668",
			"slotId": "cartridges",
			"upd": {
				"SpawnedInSession": true,
				"StackObjectsCount": 20
			}
		},
		{
			"_id": "mag0Vest30282",
			"_tpl": "5c5970672e221602b21d7855",
			"parentId": "TacticalVest689194",
			"slotId": "1",
			"location": {
				"x": 0,
				"y": 0,
				"r": "Horizontal"
			},
			"upd": {
				"SpawnedInSession": true
			}
		},
		{
			"_id": "AmmoMag0Vest279324",
			"_tpl": "59e4cf5286f7741778269d8a",
			"parentId": "mag0Vest30282",
			"slotId": "cartridges",
			"upd": {
				"SpawnedInSession": true,
				"StackObjectsCount": 35
			}
		},
		{
			"_id": "mag1Vest329014",
			"_tpl": "5c5970672e221602b21d7855",
			"parentId": "TacticalVest689194",
			"slotId": "3",
			"location": {
				"x": 0,
				"y": 0,
				"r": "Horizontal"
			},
			"upd": {
				"SpawnedInSession": true
			}
		},
		{
			"_id": "AmmoMag1Vest33337",
			"_tpl": "5656d7c34bdc2d9d198b4587",
			"parentId": "mag1Vest329014",
			"slotId": "cartridges",
			"upd": {
				"SpawnedInSession": true,
				"StackObjectsCount": 35
			}
		},
		{
			"_id": "mag3Vest584392",
			"_tpl": "5c5970672e221602b21d7855",
			"parentId": "TacticalVest689194",
			"slotId": "6",
			"location": {
				"x": 0,
				"y": 0,
				"r": "Horizontal"
			},
			"upd": {
				"SpawnedInSession": true
			}
		},
		{
			"_id": "AmmoMag3Vest695293",
			"_tpl": "59e0d99486f7744a32234762",
			"parentId": "mag3Vest584392",
			"slotId": "cartridges",
			"upd": {
				"SpawnedInSession": true,
				"StackObjectsCount": 35
			}
		},
		{
			"_id": "mag4Vest399961",
			"_tpl": "5c5970672e221602b21d7855",
			"parentId": "TacticalVest689194",
			"slotId": "8",
			"location": {
				"x": 0,
				"y": 0,
				"r": "Horizontal"
			},
			"upd": {
				"SpawnedInSession": true
			}
		},
		{
			"_id": "AmmoMag4Vest256263",
			"_tpl": "5656d7c34bdc2d9d198b4587",
			"parentId": "mag4Vest399961",
			"slotId": "cartridges",
			"upd": {
				"SpawnedInSession": true,
				"StackObjectsCount": 35
			}
		},
		{
			"_id": "Scabbard135282",
			"_tpl": "5bffdc370db834001d23eca8",
			"parentId": "5c6687d65e9d882c8841f0fd",
			"slotId": "Scabbard",
			"upd": {
				"SpawnedInSession": true
			}
		},
		{
			"_id": "Headwear125814",
			"_tpl": "5b40e61f5acfc4001a599bec",
			"parentId": "5c6687d65e9d882c8841f0fd",
			"slotId": "Headwear",
			"upd": {
				"SpawnedInSession": true
			}
		},
		{
			"_id": "FaceCover98522",
			"_tpl": "572b7f1624597762ae139822",
			"parentId": "5c6687d65e9d882c8841f0fd",
			"slotId": "FaceCover",
			"upd": {
				"SpawnedInSession": true
			}
		},
		{
			"_id": "Backpack925959",
			"_tpl": "56e33680d2720be2748b4576",
			"parentId": "5c6687d65e9d882c8841f0fd",
			"slotId": "Backpack",
			"upd": {
				"SpawnedInSession": true
			}
		},
		{
			"_id": "BP_Backpack925959_919485",
			"_tpl": "59d6507c86f7741b846413a2",
			"parentId": "Backpack925959",
			"slotId": "main",
			"location": {
				"x": 0,
				"y": 0,
				"r": "Horizontal"
			},
			"upd": {
				"SpawnedInSession": true
			}
		},
		{
			"_id": "ArmorVest945580",
			"_tpl": "59e7635f86f7742cbf2c1095",
			"parentId": "5c6687d65e9d882c8841f0fd",
			"slotId": "ArmorVest",
			"upd": {
				"Repairable": {
					"MaxDurability": 40,
					"Durability": 37
				}
			}
		},
		{
			"_id": "Pocket_938756",
			"_tpl": "591afe0186f77431bd616a11",
			"parentId": "5c6687d65e9d882c8841f121",
			"slotId": "pocket1",
			"location": {
				"x": 0,
				"y": 0,
				"r": "Horizontal"
			},
			"upd": {
				"SpawnedInSession": true
			}
		},
		{
			"_id": "Pocket_22588",
			"_tpl": "59136e1e86f774432f15d133",
			"parentId": "5c6687d65e9d882c8841f121",
			"slotId": "pocket2",
			"location": {
				"x": 0,
				"y": 0,
				"r": "Horizontal"
			},
			"upd": {
				"SpawnedInSession": true
			}
		},
		{
			"_id": "Pocket_407499",
			"_tpl": "59148f8286f7741b951ea113",
			"parentId": "5c6687d65e9d882c8841f121",
			"slotId": "pocket3",
			"location": {
				"x": 0,
				"y": 0,
				"r": "Horizontal"
			},
			"upd": {
				"SpawnedInSession": true
			}
		}
	],
	"equipment": "5c6687d65e9d882c8841f0fd",
	"stash": "5c6687d65e9d882c8841f0fc",
	"questRaidItems": "5c6687d65e9d882c8841f0fe",
	"questStashItems": "5c6687d65e9d882c8841f0ff",
	"fastPanel": {}
}