{
	"items": [
		{
			"_id": "5c6687d65e9d882c8841f0fd",
			"_tpl": "55d7217a4bdc2d86028b456d"
		},
		{
			"_id": "5c6687d65e9d882c8841f121",
			"_tpl": "557ffd194bdc2d28148b457f",
			"parentId": "5c6687d65e9d882c8841f0fd",
			"slotId": "Pockets"
		},
		{
			"_id": "5c6687d65e9d882c8841f0fc",
			"_tpl": "566abbc34bdc2d92178b4576"
		},
		{
			"_id": "5c6687d65e9d882c8841f0ff",
			"_tpl": "5963866b86f7747bfa1c4462"
		},
		{
			"_id": "5c6687d65e9d882c8841f0fe",
			"_tpl": "5963866286f7747bf429b572"
		},
		{
			"_id": "TacticalVest54343",
			"_tpl": "5c0e9f2c86f77432297fe0a3",
			"parentId": "5c6687d65e9d882c8841f0fd",
			"slotId": "TacticalVest",
			"upd": {
				"SpawnedInSession": true
			}
		},
		{
			"_id": "5bbf1d5988a45017b431dafb",
			"_tpl": "5ae08f0a5acfc408fb1398a1",
			"parentId": "5c6687d65e9d882c8841f0fd",
			"slotId": "FirstPrimaryWeapon"
		},
		{
			"_id": "MagazineWeaponScav2333",
			"_tpl": "5ae0973a5acfc4001562206c",
			"parentId": "5bbf1d5988a45017b431dafb",
			"slotId": "mod_magazine",
			"upd": {
				"SpawnedInSession": true
			}
		},
		{
			"_id": "AmmoMag13219",
			"_tpl": "59e77a2386f7742ee578960a",
			"parentId": "MagazineWeaponScav2333",
			"slotId": "cartridges",
			"upd": {
				"SpawnedInSession": true,
				"StackObjectsCount": 5
			}
		},
		{
			"_id": "5bbf1d5988a45017b431dafd",
			"_tpl": "5ae096d95acfc400185c2c81",
			"parentId": "5bbf1d5988a45017b431dafb",
			"slotId": "mod_stock",
			"upd": {
				"SpawnedInSession": true
			}
		},
		{
			"_id": "5bbf1d5988a45017b431dafe",
			"_tpl": "5ae09bff5acfc4001562219d",
			"parentId": "5bbf1d5988a45017b431dafb",
			"slotId": "mod_barrel",
			"upd": {
				"SpawnedInSession": true
			}
		},
		{
			"_id": "5bbf1d5988a45017b431daff",
			"_tpl": "5ae099875acfc4001714e593",
			"parentId": "5bbf1d5988a45017b431dafe",
			"slotId": "mod_sight_front",
			"upd": {
				"SpawnedInSession": true
			}
		},
		{
			"_id": "5bbf1d5988a45017b431db00",
			"_tpl": "5ae099925acfc4001a5fc7b3",
			"parentId": "5bbf1d5988a45017b431dafe",
			"slotId": "mod_sight_rear",
			"upd": {
				"SpawnedInSession": true
			}
		},
		{
			"_id": "mag0Vest346786",
			"_tpl": "5bae13ded4351e44f824bf38",
			"parentId": "TacticalVest54343",
			"slotId": "1",
			"location": {
				"x": 0,
				"y": 0,
				"r": "Horizontal"
			},
			"upd": {
				"SpawnedInSession": true
			}
		},
		{
			"_id": "AmmoMag0Vest137742",
			"_tpl": "5e023d34e8a400319a28ed44",
			"parentId": "mag0Vest346786",
			"slotId": "cartridges",
			"upd": {
				"SpawnedInSession": true,
				"StackObjectsCount": 10
			}
		},
		{
			"_id": "mag1Vest572211",
			"_tpl": "5bae13ded4351e44f824bf38",
			"parentId": "TacticalVest54343",
			"slotId": "3",
			"location": {
				"x": 0,
				"y": 1,
				"r": "Horizontal"
			},
			"upd": {
				"SpawnedInSession": true
			}
		},
		{
			"_id": "AmmoMag1Vest736264",
			"_tpl": "5e023cf8186a883be655e54f",
			"parentId": "mag1Vest572211",
			"slotId": "cartridges",
			"upd": {
				"SpawnedInSession": true,
				"StackObjectsCount": 10
			}
		},
		{
			"_id": "mag2Vest493614",
			"_tpl": "5bae13ded4351e44f824bf38",
			"parentId": "TacticalVest54343",
			"slotId": "5",
			"location": {
				"x": 0,
				"y": 0,
				"r": "Horizontal"
			},
			"upd": {
				"SpawnedInSession": true
			}
		},
		{
			"_id": "AmmoMag2Vest777054",
			"_tpl": "5887431f2459777e1612938f",
			"parentId": "mag2Vest493614",
			"slotId": "cartridges",
			"upd": {
				"SpawnedInSession": true,
				"StackObjectsCount": 10
			}
		},
		{
			"_id": "mag2Vest261139",
			"_tpl": "5bae13ded4351e44f824bf38",
			"parentId": "TacticalVest54343",
			"slotId": "5",
			"location": {
				"x": 0,
				"y": 1,
				"r": "Horizontal"
			},
			"upd": {
				"SpawnedInSession": true
			}
		},
		{
			"_id": "AmmoMag2Vest9819",
			"_tpl": "5e023cf8186a883be655e54f",
			"parentId": "mag2Vest261139",
			"slotId": "cartridges",
			"upd": {
				"SpawnedInSession": true,
				"StackObjectsCount": 10
			}
		},
		{
			"_id": "mag3Vest571399",
			"_tpl": "5bae13ded4351e44f824bf38",
			"parentId": "TacticalVest54343",
			"slotId": "7",
			"location": {
				"x": 0,
				"y": 0,
				"r": "Horizontal"
			},
			"upd": {
				"SpawnedInSession": true
			}
		},
		{
			"_id": "AmmoMag3Vest348044",
			"_tpl": "5e023cf8186a883be655e54f",
			"parentId": "mag3Vest571399",
			"slotId": "cartridges",
			"upd": {
				"SpawnedInSession": true,
				"StackObjectsCount": 10
			}
		},
		{
			"_id": "mag3Vest606663",
			"_tpl": "5bae13ded4351e44f824bf38",
			"parentId": "TacticalVest54343",
			"slotId": "7",
			"location": {
				"x": 0,
				"y": 1,
				"r": "Horizontal"
			},
			"upd": {
				"SpawnedInSession": true
			}
		},
		{
			"_id": "AmmoMag3Vest510439",
			"_tpl": "560d61e84bdc2da74d8b4571",
			"parentId": "mag3Vest606663",
			"slotId": "cartridges",
			"upd": {
				"SpawnedInSession": true,
				"StackObjectsCount": 10
			}
		},
		{
			"_id": "Scabbard935403",
			"_tpl": "5c0116620db834001808a647",
			"parentId": "5c6687d65e9d882c8841f0fd",
			"slotId": "Scabbard",
			"upd": {
				"SpawnedInSession": true
			}
		},
		{
			"_id": "Headwear628930",
			"_tpl": "5b40e61f5acfc4001a599bec",
			"parentId": "5c6687d65e9d882c8841f0fd",
			"slotId": "Headwear",
			"upd": {
				"SpawnedInSession": true
			}
		},
		{
			"_id": "Eyewear947703",
			"_tpl": "5b432be65acfc433000ed01f",
			"parentId": "5c6687d65e9d882c8841f0fd",
			"slotId": "Eyewear",
			"upd": {
				"SpawnedInSession": true
			}
		},
		{
			"_id": "ArmorVest588553",
			"_tpl": "5ab8e79e86f7742d8b372e78",
			"parentId": "5c6687d65e9d882c8841f0fd",
			"slotId": "ArmorVest",
			"upd": {
				"Repairable": {
					"MaxDurability": 75,
					"Durability": 39
				}
			}
		},
		{
			"_id": "Pocket_320451",
			"_tpl": "5673de654bdc2d180f8b456d",
			"parentId": "5c6687d65e9d882c8841f121",
			"slotId": "pocket1",
			"location": {
				"x": 0,
				"y": 0,
				"r": "Horizontal"
			},
			"upd": {
				"SpawnedInSession": true
			}
		},
		{
			"_id": "Pocket_626818",
			"_tpl": "593aa4be86f77457f56379f8",
			"parentId": "5c6687d65e9d882c8841f121",
			"slotId": "pocket2",
			"location": {
				"x": 0,
				"y": 0,
				"r": "Horizontal"
			},
			"upd": {
				"SpawnedInSession": true
			}
		},
		{
			"_id": "Pocket_822344",
			"_tpl": "5d1b3a5d86f774252167ba22",
			"parentId": "5c6687d65e9d882c8841f121",
			"slotId": "pocket3",
			"location": {
				"x": 0,
				"y": 0,
				"r": "Horizontal"
			},
			"upd": {
				"SpawnedInSession": true
			}
		}
	],
	"equipment": "5c6687d65e9d882c8841f0fd",
	"stash": "5c6687d65e9d882c8841f0fc",
	"questRaidItems": "5c6687d65e9d882c8841f0fe",
	"questStashItems": "5c6687d65e9d882c8841f0ff",
	"fastPanel": {}
}